{
    "corrections": [
        {
            "inputs": [
                {
                    "type": "string", 
                    "name": "sf", 
                    "description": "sf, e.g. central/up/down"
                }, 
                {
                    "type": "real", 
                    "name": "pt", 
                    "description": "Electron pT value"
                }, 
                {
                    "type": "real", 
                    "name": "eta", 
                    "description": "Electron eta value"
                }
            ], 
            "name": "EleTriggerSF", 
            "version": 2, 
            "output": {
                "type": "real", 
                "name": "ScaleFactor", 
                "description": "Electron Trigger SF for the corresponding bin"
            }, 
            "data": {
                "content": [
                    {
                        "value": {
                            "content": [
                                1.035202145576477, 
                                0.9966813921928406, 
                                1.0043150186538696, 
                                1.0248112678527832, 
                                0.978215754032135, 
                                1.0174180269241333, 
                                0.9882352948188782, 
                                0.9849624037742615, 
                                0.98219895362854, 
                                0.9895724654197693, 
                                0.9775739312171936, 
                                0.9979919791221619, 
                                0.9375, 
                                0.9716775417327881, 
                                0.9956709742546082, 
                                0.9729729890823364, 
                                0.9835729002952576, 
                                0.9890000224113464, 
                                0.9514451026916504, 
                                0.9762675166130066, 
                                0.981151819229126, 
                                0.9832810759544373, 
                                0.9886597990989685, 
                                0.9979899525642395, 
                                0.9677419066429138, 
                                0.9784714579582214, 
                                0.9821052551269531, 
                                0.9833159446716309, 
                                0.9843260049819946, 
                                0.9979959726333618, 
                                0.9591598510742188, 
                                0.9704918265342712, 
                                0.977540135383606, 
                                0.9745762944221497, 
                                0.9862433671951294, 
                                0.9949849843978882, 
                                0.9529411792755127, 
                                0.978094220161438, 
                                0.9788807034492493, 
                                0.9759414196014404, 
                                0.9853402972221375, 
                                1.0010050535202026, 
                                0.9382422566413879, 
                                0.9682713150978088, 
                                0.9682203531265259, 
                                0.9551934599876404, 
                                0.9796954393386841, 
                                0.9890000224113464, 
                                0.9929078221321106, 
                                0.9860215187072754, 
                                0.9947313070297241, 
                                0.9864158630371094, 
                                0.9865979552268982, 
                                1.012170433998108, 
                                1.0414438247680664, 
                                1.0033974647521973, 
                                0.9989047050476074, 
                                1.0279954671859741, 
                                0.9945414662361145, 
                                1.0122699737548828
                            ], 
                            "inputs": [
                                "eta", 
                                "pt"
                            ], 
                            "edges": [
                                [
                                    -2.5, 
                                    -2.0, 
                                    -1.566, 
                                    -1.444, 
                                    -0.8, 
                                    0.0, 
                                    0.8, 
                                    1.444, 
                                    1.566, 
                                    2.0, 
                                    2.5
                                ], 
                                [
                                    32.0, 
                                    50.0, 
                                    80.0, 
                                    110.0, 
                                    150.0, 
                                    200.0, 
                                    500.0
                                ]
                            ], 
                            "nodetype": "multibinning", 
                            "flow": "clamp"
                        }, 
                        "key": "central"
                    }, 
                    {
                        "value": {
                            "content": [
                                1.05643740358591, 
                                0.9998960327337124, 
                                1.0151777882687103, 
                                1.057618803266249, 
                                1.0008471544571402, 
                                1.038725765687251, 
                                1.0021508888297344, 
                                0.9882748239800482, 
                                0.987263896255112, 
                                0.9974099692912104, 
                                0.9931796076371201, 
                                1.004093586903417, 
                                0.9475765599798381, 
                                0.9763731341274621, 
                                1.0109771610377942, 
                                0.9949076304230325, 
                                1.0208175756613076, 
                                1.0034935554519822, 
                                0.9615781331272089, 
                                0.979038722870394, 
                                0.9854873666798281, 
                                0.9885084674860629, 
                                0.9979706813477658, 
                                1.0022907673302255, 
                                0.9763403976424452, 
                                0.9804267460685598, 
                                0.985058976274343, 
                                0.9899887902308534, 
                                0.9912463238994963, 
                                1.0000165886103791, 
                                0.9677583420737501, 
                                0.9724471146446096, 
                                0.9804938565309959, 
                                0.9813873724026099, 
                                0.9933751547693936, 
                                0.9971698961490364, 
                                0.9630742097110712, 
                                0.9808654264188253, 
                                0.9832162508999513, 
                                0.9811688111330661, 
                                0.994748489573449, 
                                1.0052093752615798, 
                                0.9483188166212261, 
                                0.9729669074924828, 
                                0.9831809405060571, 
                                0.9767124935919119, 
                                1.0165020199529984, 
                                1.0033440106991276, 
                                1.0068234161429668, 
                                0.9893339389130621, 
                                0.9997962496562961, 
                                0.994585213685595, 
                                1.0024624222084892, 
                                1.0190329317320814, 
                                1.0626790827774995, 
                                1.0066121052930692, 
                                1.0100294275967698, 
                                1.061067643837869, 
                                1.018388819184476, 
                                1.0334266028322567
                            ], 
                            "inputs": [
                                "eta", 
                                "pt"
                            ], 
                            "edges": [
                                [
                                    -2.5, 
                                    -2.0, 
                                    -1.566, 
                                    -1.444, 
                                    -0.8, 
                                    0.0, 
                                    0.8, 
                                    1.444, 
                                    1.566, 
                                    2.0, 
                                    2.5
                                ], 
                                [
                                    32.0, 
                                    50.0, 
                                    80.0, 
                                    110.0, 
                                    150.0, 
                                    200.0, 
                                    500.0
                                ]
                            ], 
                            "nodetype": "multibinning", 
                            "flow": "clamp"
                        }, 
                        "key": "up"
                    }, 
                    {
                        "value": {
                            "content": [
                                1.013966887567044, 
                                0.9934667516519687, 
                                0.9934522490390291, 
                                0.9920037324393174, 
                                0.9555843536071299, 
                                0.9961102881610155, 
                                0.974319700808022, 
                                0.9816499835684748, 
                                0.9771340110019681, 
                                0.9817349615483282, 
                                0.9619682547972671, 
                                0.9918903713409066, 
                                0.9274234400201619, 
                                0.9669819493381141, 
                                0.9803647874714221, 
                                0.9510383477416403, 
                                0.9463282249292075, 
                                0.9745064893707106, 
                                0.9413120722560919, 
                                0.9734963103556192, 
                                0.9768162717784239, 
                                0.9780536844228116, 
                                0.9793489168501712, 
                                0.9936891377982536, 
                                0.9591434156433825, 
                                0.976516169847883, 
                                0.9791515339795632, 
                                0.9766430991124083, 
                                0.977405686064493, 
                                0.9959753566563446, 
                                0.9505613600746874, 
                                0.9685365384239328, 
                                0.9745864142362161, 
                                0.9677652164416894, 
                                0.9791115796208651, 
                                0.99280007264674, 
                                0.9428081488399542, 
                                0.9753230139040506, 
                                0.9745451559985472, 
                                0.9707140280698148, 
                                0.9759321048708259, 
                                0.9968007317788253, 
                                0.9281656966615498, 
                                0.9635757227031349, 
                                0.9532597657469947, 
                                0.9336744263833688, 
                                0.9428888587243699, 
                                0.9746560341235653, 
                                0.9789922281212544, 
                                0.9827090985014887, 
                                0.9896663644031521, 
                                0.9782465123886237, 
                                0.970733488245307, 
                                1.0053079362641344, 
                                1.0202085667586334, 
                                1.0001828242113253, 
                                0.987779982498445, 
                                0.9949232905340792, 
                                0.9706941132877529, 
                                0.9911133446775089
                            ], 
                            "inputs": [
                                "eta", 
                                "pt"
                            ], 
                            "edges": [
                                [
                                    -2.5, 
                                    -2.0, 
                                    -1.566, 
                                    -1.444, 
                                    -0.8, 
                                    0.0, 
                                    0.8, 
                                    1.444, 
                                    1.566, 
                                    2.0, 
                                    2.5
                                ], 
                                [
                                    32.0, 
                                    50.0, 
                                    80.0, 
                                    110.0, 
                                    150.0, 
                                    200.0, 
                                    500.0
                                ]
                            ], 
                            "nodetype": "multibinning", 
                            "flow": "clamp"
                        }, 
                        "key": "down"
                    }
                ], 
                "input": "sf", 
                "nodetype": "category"
            }, 
            "description": "Electron Trigger SFs"
        }
    ], 
    "schema_version": 2
}