{
    "corrections": [
        {
            "inputs": [
                {
                    "type": "string", 
                    "name": "sf", 
                    "description": "sf, e.g. central/up/down"
                }, 
                {
                    "type": "real", 
                    "name": "pt", 
                    "description": "Electron pT value"
                }, 
                {
                    "type": "real", 
                    "name": "eta", 
                    "description": "Electron eta value"
                }
            ], 
            "name": "EleTriggerSF", 
            "version": 2, 
            "output": {
                "type": "real", 
                "name": "ScaleFactor", 
                "description": "Electron Trigger SF for the corresponding bin"
            }, 
            "data": {
                "content": [
                    {
                        "value": {
                            "content": [
                                0.9857549667358398, 
                                0.9643765687942505, 
                                0.9821640849113464, 
                                0.9750000238418579, 
                                1.0011428594589233, 
                                1.023983359336853, 
                                0.9323493242263794, 
                                0.9458823800086975, 
                                0.9508379697799683, 
                                0.9620535969734192, 
                                0.9511930346488953, 
                                1.0020325183868408, 
                                0.9487836360931396, 
                                0.955719530582428, 
                                0.9420289993286133, 
                                0.9479553699493408, 
                                1.0490566492080688, 
                                0.9356486201286316, 
                                0.968137264251709, 
                                0.9776207208633423, 
                                0.9855072498321533, 
                                0.9747530221939087, 
                                0.9967213273048401, 
                                0.99798184633255, 
                                0.9699519276618958, 
                                0.9744779467582703, 
                                0.9765886068344116, 
                                0.9856511950492859, 
                                0.9816017150878906, 
                                0.9919678568840027, 
                                0.9586374759674072, 
                                0.9578947424888611, 
                                0.9607182741165161, 
                                0.9688888788223267, 
                                0.9568965435028076, 
                                0.990963876247406, 
                                0.9550561904907227, 
                                0.9664670825004578, 
                                0.9727891087532043, 
                                0.9624723792076111, 
                                0.9735973477363586, 
                                0.9919273257255554, 
                                0.9435173273086548, 
                                0.948019802570343, 
                                0.9875621795654297, 
                                0.9649805426597595, 
                                0.9707207083702087, 
                                0.9857578873634338, 
                                0.9134146571159363, 
                                0.9468713402748108, 
                                0.9708192944526672, 
                                0.9700332880020142, 
                                0.9647576808929443, 
                                0.9879999756813049, 
                                0.9368723034858704, 
                                0.9547803401947021, 
                                0.9653109908103943, 
                                0.97782963514328, 
                                0.908108115196228, 
                                0.9868553876876831
                            ], 
                            "inputs": [
                                "eta", 
                                "pt"
                            ], 
                            "edges": [
                                [
                                    -2.5, 
                                    -2.0, 
                                    -1.566, 
                                    -1.444, 
                                    -0.8, 
                                    0.0, 
                                    0.8, 
                                    1.444, 
                                    1.566, 
                                    2.0, 
                                    2.5
                                ], 
                                [
                                    40.0, 
                                    50.0, 
                                    80.0, 
                                    110.0, 
                                    150.0, 
                                    200.0, 
                                    500.0
                                ]
                            ], 
                            "nodetype": "multibinning", 
                            "flow": "clamp"
                        }, 
                        "key": "central"
                    }, 
                    {
                        "value": {
                            "content": [
                                0.989399726931403, 
                                0.9714569284206526, 
                                0.9952011815774617, 
                                0.9882349851919703, 
                                1.0241297048651201, 
                                1.0395793116273697, 
                                0.9354718101501962, 
                                0.9504086886403231, 
                                0.9606163847836485, 
                                0.9758931407858241, 
                                0.9653822829249595, 
                                1.0115759136634344, 
                                1.030342656239647, 
                                0.9629927114106522, 
                                0.9657070588143318, 
                                0.9887450658726719, 
                                1.092093489166385, 
                                0.9619813341510418, 
                                0.9700929090631921, 
                                0.9814230511706065, 
                                0.9904477770472312, 
                                0.979981420652907, 
                                1.0091780902078025, 
                                1.0036733267425797, 
                                0.9717657124261037, 
                                0.9770825687472042, 
                                0.9813997507197821, 
                                0.992455295673563, 
                                0.9922101830708218, 
                                0.9939915159573708, 
                                0.9604512607316151, 
                                0.960499364477795, 
                                0.9655294180018866, 
                                0.9756929794466038, 
                                0.9675050114857388, 
                                0.9931520785282999, 
                                0.9570118353022058, 
                                0.9702694128077219, 
                                0.9778792634120786, 
                                0.9678366028426187, 
                                0.9861352826333205, 
                                0.9975001617584451, 
                                1.025076347455162, 
                                0.9552929833985673, 
                                1.0114199275236795, 
                                1.0057702385830907, 
                                1.0121557728303658, 
                                1.010528739310881, 
                                0.9165371430397531, 
                                0.9513976489064364, 
                                0.9805977094563475, 
                                0.9841113187651455, 
                                0.9791636113043805, 
                                0.9970725563264663, 
                                0.9405170636814335, 
                                0.9618606998211042, 
                                0.9783480874765096, 
                                0.9914533076432216, 
                                0.9305720781064011, 
                                1.001210758790465
                            ], 
                            "inputs": [
                                "eta", 
                                "pt"
                            ], 
                            "edges": [
                                [
                                    -2.5, 
                                    -2.0, 
                                    -1.566, 
                                    -1.444, 
                                    -0.8, 
                                    0.0, 
                                    0.8, 
                                    1.444, 
                                    1.566, 
                                    2.0, 
                                    2.5
                                ], 
                                [
                                    40.0, 
                                    50.0, 
                                    80.0, 
                                    110.0, 
                                    150.0, 
                                    200.0, 
                                    500.0
                                ]
                            ], 
                            "nodetype": "multibinning", 
                            "flow": "clamp"
                        }, 
                        "key": "up"
                    }, 
                    {
                        "value": {
                            "content": [
                                0.9821102065402767, 
                                0.9572962091678484, 
                                0.9691269882452311, 
                                0.9617650624917455, 
                                0.9781560140527265, 
                                1.0083874070463363, 
                                0.9292268383025626, 
                                0.9413560713770719, 
                                0.941059554776288, 
                                0.9482140531610143, 
                                0.937003786372831, 
                                0.9924891231102473, 
                                0.8672246159466324, 
                                0.9484463497542037, 
                                0.9183509398428947, 
                                0.9071656740260098, 
                                1.0060198092497528, 
                                0.9093159061062214, 
                                0.9661816194402258, 
                                0.9738183905560781, 
                                0.9805667226170754, 
                                0.9695246237349103, 
                                0.9842645644018776, 
                                0.9922903659225205, 
                                0.9681381428976878, 
                                0.9718733247693363, 
                                0.9717774629490411, 
                                0.9788470944250087, 
                                0.9709932471049595, 
                                0.9899441978106346, 
                                0.9568236912031993, 
                                0.9552901204999271, 
                                0.9559071302311456, 
                                0.9620847781980495, 
                                0.9462880755198765, 
                                0.9887756739665121, 
                                0.9531005456792395, 
                                0.9626647521931936, 
                                0.96769895409433, 
                                0.9571081555726034, 
                                0.9610594128393968, 
                                0.9863544896926657, 
                                0.8619583071621475, 
                                0.9407466217421188, 
                                0.96370443160718, 
                                0.9241908467364285, 
                                0.9292856439100516, 
                                0.9609870354159866, 
                                0.9102921711921195, 
                                0.9423450316431852, 
                                0.961040879448987, 
                                0.9559552572388829, 
                                0.9503517504815082, 
                                0.9789273950361436, 
                                0.9332275432903072, 
                                0.9476999805683001, 
                                0.952273894144279, 
                                0.9642059626433385, 
                                0.885644152286055, 
                                0.9725000165849012
                            ], 
                            "inputs": [
                                "eta", 
                                "pt"
                            ], 
                            "edges": [
                                [
                                    -2.5, 
                                    -2.0, 
                                    -1.566, 
                                    -1.444, 
                                    -0.8, 
                                    0.0, 
                                    0.8, 
                                    1.444, 
                                    1.566, 
                                    2.0, 
                                    2.5
                                ], 
                                [
                                    40.0, 
                                    50.0, 
                                    80.0, 
                                    110.0, 
                                    150.0, 
                                    200.0, 
                                    500.0
                                ]
                            ], 
                            "nodetype": "multibinning", 
                            "flow": "clamp"
                        }, 
                        "key": "down"
                    }
                ], 
                "input": "sf", 
                "nodetype": "category"
            }, 
            "description": "Electron Trigger SFs"
        }
    ], 
    "schema_version": 2
}